rakish/.__init__.py.swp
rakish/__init__.py
rakish/__main__.py
rakish/app.py
rakish/blueprints.py
rakish/cli.py
rakish/config.py
rakish/ctx.py
rakish/debughelpers.py
rakish/globals.py
rakish/helpers.py
rakish/logging.py
rakish/scaffold.py
rakish/sessions.py
rakish/signals.py
rakish/templating.py
rakish/testing.py
rakish/views.py
rakish/wrappers.py
rakish/json/.__init__.py.swp
rakish/json/.tag.py.swp
rakish/json/__init__.py
rakish/json/tag.py
rakish-1.0.0.dev3.dist-info/LICENSE
rakish-1.0.0.dev3.dist-info/WHEEL
rakish-1.0.0.dev3.dist-info/METADATA
rakish-1.0.0.dev3.dist-info/RECORD
