Metadata-Version: 2.1
Name: rakish
Version: 1.0.0.dev3
Summary: Confido is a web framewotk
Home-page: https://github.com/secretuminc/rakish
License: UNKNOWN
Author: Gerrishon Sirere
Author-email: secretum.inc@pm.me
Requires-Python: >=3.6
Classifier: Intended Audience :: Information Technology
Classifier: Intended Audience :: System Administrators
Classifier: Operating System :: OS Independent
Classifier: Programming Language :: Python :: 3
Classifier: Programming Language :: Python
Classifier: Topic :: Software Development :: Libraries :: Application Frameworks
Classifier: Topic :: Software Development :: Libraries :: Python Modules
Classifier: Topic :: Software Development :: Libraries
Classifier: Topic :: Software Development
Classifier: Development Status :: 4 - Beta
Classifier: Intended Audience :: Developers
Classifier: Programming Language :: Python :: 3 :: Only
Classifier: Programming Language :: Python :: 3.7
Classifier: Programming Language :: Python :: 3.8
Classifier: Programming Language :: Python :: 3.9
Classifier: License :: OSI Approved :: MIT License
Project-URL: Documentation, https://rakish.rtfd.io
Provides-Extra: all
Provides-Extra: dev
Provides-Extra: doc
Provides-Extra: test
